<?xml version="1.0" encoding="UTF-8"?>
<Locator>
<LoginPage>
<Userid>//input[@id='j_username']</Userid>
<Password>//input[@id='j_password']</Password>
<Login>//input[@name='submit']</Login>
</LoginPage>
<HomePage>
<Image>//a[@href='/PremiseMaster/interimFilter?value=KVH']</Image>
<MainMenu>//ul[@id='menu']/li/a[text()='Menu']</MainMenu>
<AdvanceSearch>//ul[@id='menu']//ul//li//a[text()='Advanced Search']</AdvanceSearch>
</HomePage>
<SearchLocation>
<Dropdown>//select[@id='country']</Dropdown>
<City>//Input[@id='cityNameEnglish']</City>
<HouseNo>//Input[@id='houseNumber']</HouseNo>
<BuildingName>//Input[@id='buildingName']</BuildingName>
<StreetName>//Input[@id='streetName']</StreetName>
<PostalCode>//Input[@id='postalCodeId']</PostalCode>
<State>//Input[@id='province']</State>
<SearchButton>//Input[@id='search']</SearchButton>
<CancelButton>//Input[@id='cancelButton']</CancelButton>
<SearchAgain>//Input[@id='searchAgain']</SearchAgain>
</SearchLocation>
<CreateSite>
<BuildingType>//select[@id='buildingTypeSelectID']</BuildingType>
<BuildingStatus>//select[@id='buildingStatusSelectID']</BuildingStatus>
<AccessType>//select[@id='accessTypeSelectID']</AccessType>
<BuildingCategory>//select[@id='buildingCategory']</BuildingCategory>
<Schema>//select[@id='cnmtSchema']</Schema>
<StreetName>//select[@id='CNMTStreetName']</StreetName>
<SettlementName>//input[@id='building.cnmtSettlementName']</SettlementName>
<ReferenceBoxNo>//input[@id='building.cnmtReferenceBoxNo']</ReferenceBoxNo>
<roomId>//input[@id='roomId']</roomId>
<OCN>//textarea[@id='selectedSiteOCN']</OCN>
<Status>//select[@id='siteStatus']</Status>
<SiteType>//select[@id='siteTypeID']</SiteType>
<Floor>//select[@id='floorDropdown']</Floor>
<CityID>//select[@id='manCityId']</CityID>
<AccessID>//select[@id='siteAccessID']</AccessID>
<Submit>//input[@name='submit']</Submit>
</CreateSite>
</Locator>
<Locator>